Metadata-Version: 1.1
Name: django-constance-cli
Version: 0.0.6
Summary: Get/Set In-database config settings handled by Django Constance
Home-page: https://github.com/NZME/django-constance-cli
Author: NZME
Author-email: sysadmin@grabone.co.nz
License: UNKNOWN
Keywords: django,constance,cli
Platform: any
Classifier: Development Status :: 3 - Alpha
Classifier: Environment :: Web Environment
Classifier: Intended Audience :: Developers
Classifier: Operating System :: OS Independent
Classifier: Programming Language :: Python
Classifier: Programming Language :: Python :: 2.7
Classifier: Programming Language :: Python :: 3.5
Classifier: Framework :: Django
